{
	"info": {
		"_postman_id": "35a97985-c671-4eac-ba33-6fbc07605def",
		"name": "Zitrus",
		"schema": "https://schema.getpostman.com/json/collection/v2.1.0/collection.json"
	},
	"item": [
		{
			"name": "usuario",
			"item": [
				{
					"name": "Create",
					"request": {
						"method": "POST",
						"header": [],
						"body": {
							"mode": "raw",
							"raw": "{\r\n    \"login\":\"jesse\",\r\n    \"senha\":1234,\r\n    \"admin\":true\r\n}",
							"options": {
								"raw": {
									"language": "json"
								}
							}
						},
						"url": {
							"raw": "localhost:8000/api/usuario/",
							"host": [
								"localhost"
							],
							"port": "8000",
							"path": [
								"api",
								"usuario",
								""
							]
						}
					},
					"response": []
				},
				{
					"name": "FindById",
					"request": {
						"method": "GET",
						"header": [],
						"url": null
					},
					"response": []
				},
				{
					"name": "FindAll",
					"request": {
						"method": "GET",
						"header": [],
						"url": {
							"raw": "localhost:8000/api/usuario/",
							"host": [
								"localhost"
							],
							"port": "8000",
							"path": [
								"api",
								"usuario",
								""
							]
						}
					},
					"response": []
				},
				{
					"name": "Update",
					"request": {
						"method": "PUT",
						"header": [],
						"body": {
							"mode": "raw",
							"raw": "{\r\n    \"login\":\"otto\",\r\n    \"senha\":4567,\r\n    \"admin\":true\r\n}",
							"options": {
								"raw": {
									"language": "json"
								}
							}
						},
						"url": {
							"raw": "localhost:8000/api/usuario/3",
							"host": [
								"localhost"
							],
							"port": "8000",
							"path": [
								"api",
								"usuario",
								"3"
							]
						}
					},
					"response": []
				},
				{
					"name": "Delete",
					"request": {
						"method": "DELETE",
						"header": [],
						"url": {
							"raw": "localhost:8000/api/usuario/3",
							"host": [
								"localhost"
							],
							"port": "8000",
							"path": [
								"api",
								"usuario",
								"3"
							]
						}
					},
					"response": []
				},
				{
					"name": "FindByLogin",
					"request": {
						"method": "GET",
						"header": [],
						"url": null
					},
					"response": []
				}
			]
		},
		{
			"name": "endereco",
			"item": [
				{
					"name": "Create",
					"request": {
						"method": "POST",
						"header": [],
						"body": {
							"mode": "raw",
							"raw": "{\r\n   \"logradouro\":\"Rua Mariano Manoel da Silva\",\r\n   \"complemento\":\"Numero 433\",\r\n   \"cep\":\"55125000\",\r\n   \"bairro\":\"Centro\",\r\n   \"localidade\":\"Toritama\",\r\n   \"uf\":\"PE\"\r\n}",
							"options": {
								"raw": {
									"language": "json"
								}
							}
						},
						"url": {
							"raw": "localhost:8100/api/endereco/",
							"host": [
								"localhost"
							],
							"port": "8100",
							"path": [
								"api",
								"endereco",
								""
							]
						}
					},
					"response": []
				},
				{
					"name": "FindById",
					"request": {
						"method": "GET",
						"header": [],
						"url": null
					},
					"response": []
				},
				{
					"name": "FindAll",
					"request": {
						"method": "GET",
						"header": [],
						"url": null
					},
					"response": []
				},
				{
					"name": "Update",
					"request": {
						"method": "PUT",
						"header": [],
						"body": {
							"mode": "raw",
							"raw": "{\r\n   \"logradouro\":\"Travessa Abilio Floro\",\r\n   \"complemento\":\"Numero 1313\",\r\n   \"cep\":\"55123999\",\r\n   \"bairro\":\"Centro\",\r\n   \"localidade\":\"Toritama\",\r\n   \"uf\":\"PE\"\r\n}",
							"options": {
								"raw": {
									"language": "json"
								}
							}
						},
						"url": {
							"raw": "localhost:8100/api/endereco/3",
							"host": [
								"localhost"
							],
							"port": "8100",
							"path": [
								"api",
								"endereco",
								"3"
							]
						}
					},
					"response": []
				},
				{
					"name": "Delete",
					"request": {
						"method": "DELETE",
						"header": [],
						"url": {
							"raw": "localhost:8100/api/endereco/3",
							"host": [
								"localhost"
							],
							"port": "8100",
							"path": [
								"api",
								"endereco",
								"3"
							]
						}
					},
					"response": []
				}
			]
		},
		{
			"name": "cliente",
			"item": [
				{
					"name": "Create",
					"request": {
						"method": "POST",
						"header": [],
						"body": {
							"mode": "raw",
							"raw": "{\r\n    \"nome\":\"Braz Fracncisco dos Santos\",\r\n    \"email\":\"brazsantos@hotmail.com.br\",\r\n    \"dataNascimento\":\"01/11/1960\",\r\n    \"cpf\":\"14481646560\",\r\n    \"endereco\":{\r\n                 \"id\":1\r\n               }\r\n}",
							"options": {
								"raw": {
									"language": "json"
								}
							}
						},
						"url": {
							"raw": "localhost:8200/api/cliente/",
							"host": [
								"localhost"
							],
							"port": "8200",
							"path": [
								"api",
								"cliente",
								""
							]
						}
					},
					"response": []
				},
				{
					"name": "FindById",
					"request": {
						"method": "GET",
						"header": [],
						"url": null
					},
					"response": []
				},
				{
					"name": "FindByCpf",
					"request": {
						"method": "GET",
						"header": [],
						"url": null
					},
					"response": []
				},
				{
					"name": "FindAll",
					"request": {
						"method": "GET",
						"header": [],
						"url": null
					},
					"response": []
				},
				{
					"name": "Update",
					"request": {
						"method": "GET",
						"header": [],
						"url": null
					},
					"response": []
				},
				{
					"name": "Delete",
					"request": {
						"method": "DELETE",
						"header": [],
						"url": {
							"raw": "localhost:8100/api/endereco/3",
							"host": [
								"localhost"
							],
							"port": "8100",
							"path": [
								"api",
								"endereco",
								"3"
							]
						}
					},
					"response": []
				}
			]
		},
		{
			"name": "gateway",
			"item": [
				{
					"name": "getUsuario",
					"request": {
						"method": "GET",
						"header": [],
						"url": null
					},
					"response": []
				},
				{
					"name": "postEndereco",
					"request": {
						"method": "POST",
						"header": [],
						"body": {
							"mode": "raw",
							"raw": "{\r\n   \"logradouro\":\"Rua Manoel Borba\",\r\n   \"complemento\":\"Numero 1313\",\r\n   \"cep\":\"55125000\",\r\n   \"bairro\":\"Centro\",\r\n   \"localidade\":\"Toritama\",\r\n   \"uf\":\"PE\"\r\n}",
							"options": {
								"raw": {
									"language": "json"
								}
							}
						},
						"url": {
							"raw": "localhost:8765/endereco-api/api/endereco/",
							"host": [
								"localhost"
							],
							"port": "8765",
							"path": [
								"endereco-api",
								"api",
								"endereco",
								""
							]
						}
					},
					"response": []
				},
				{
					"name": "getEnderecos",
					"request": {
						"method": "GET",
						"header": [],
						"url": null
					},
					"response": []
				},
				{
					"name": "postCliente",
					"request": {
						"method": "POST",
						"header": [],
						"url": null
					},
					"response": []
				},
				{
					"name": "getClientes",
					"request": {
						"method": "GET",
						"header": [],
						"url": null
					},
					"response": []
				}
			]
		},
		{
			"name": "cadastro-Cliente",
			"item": [
				{
					"name": "getClientes",
					"request": {
						"method": "GET",
						"header": [],
						"url": null
					},
					"response": []
				}
			]
		}
	]
}